README.rst
setup.py
doo/__init__.py
doo/app.py
doo/cap.py
doo/data.py
doo/doo.postman_collection.json
doo/example.xlsx
doo/example.yml
doo/mock.py
doo.egg-info/PKG-INFO
doo.egg-info/SOURCES.txt
doo.egg-info/dependency_links.txt
doo.egg-info/entry_points.txt
doo.egg-info/requires.txt
doo.egg-info/top_level.txt