Metadata-Version: 1.1
Name: doo
Version: 0.3.6
Summary: doo
Home-page: https://github.com/tonglei100/xiaomi
Author: Leo Tong
Author-email: tonglei@qq.com
License: Apache License, Version 2.0
Platform: UNKNOWN
Classifier: Environment :: Web Environment
Classifier: Intended Audience :: Developers
Classifier: Operating System :: OS Independent
Classifier: Topic :: Software Development :: Libraries :: Python Modules
Classifier: Programming Language :: Python :: 3
